pysubcipher/__init__.py
pysubcipher/pysubcipher.py
pysubcipher-2.4.0.dist-info/METADATA
pysubcipher-2.4.0.dist-info/WHEEL
pysubcipher-2.4.0.dist-info/licenses/LICENSE
pysubcipher-2.4.0.dist-info/RECORD
