Metadata-Version: 2.1
Name: pysubcipher
Version: 2.4.0
Summary: pysubcipher allows for simple encryption and decryption of text using a basic substitution cipher algorithm.
Author: mxngo
License-File: LICENSE
Classifier: Development Status :: 5 - Production/Stable
Classifier: License :: OSI Approved :: MIT License
Classifier: Operating System :: OS Independent
Classifier: Programming Language :: Python :: 3
Classifier: Topic :: Security :: Cryptography
Requires-Python: >=3.10
